{"id":100021,"link":"KitaDetailsNeu.aspx?ID= 100021","num":4071750,"parent":"El Carrusel e.V.","address":"Gierkezeile 30","district":"Charlottenburg","type":"Eltern-Initiativ-Kindertagesstätte","parentType":"(EKT)","mapLink":"http://www.berlin.de/stadtplan/explorer?ADR_ZIP=10585&ADR_STREET=Gierkezeile&ADR_HOUSE=030","postcode":["10585"],"phone":"030657 99 680","email":"info@elcarrusel.de","webLink":"http://www.elcarrusel.de","educational":["bilingual (spanisch)"],"topics":[""],"languages":["deutsch - spanisch"],"open":[["07:30","16:30"],["07:30","16:30"],["07:30","16:30"],["07:30","16:30"],["07:30","16:30"]],"structure":{"overall":24,"under":6,"over":18,"min":20,"mix":""},"places":[],"jobs":[],"geo":{"lat":52.51576,"lon":13.303},"streetName":"Gierkezeile","streetNumber":"30"}