{"id":1344,"link":"KitaDetailsNeu.aspx?ID= 1344","num":7130360,"parent":"Kath. Kirchengemeinde St. Alfons","address":"Emilienstr. 9","district":"Marienfelde","type":"Kindertagesstätte","parentType":"(Deutscher Caritasverband)","mapLink":"http://www.berlin.de/stadtplan/explorer?ADR_ZIP=12277&ADR_STREET=Emilienstra%c3%9fe&ADR_HOUSE=009","postcode":["12277"],"phone":"030722 70 61","email":"kitastalfons@arcor.de","webLink":"http://www.kita-st-alfons.de","educational":["Situationsansatz"],"topics":["Integration von Kindern mit Behinderung"," Religionspädagogik"],"languages":[""],"open":[["07:00","17:00"],["07:00","17:00"],["07:00","17:00"],["07:00","17:00"],["07:00","16:30"]],"structure":{"overall":65,"under":13,"over":52,"min":12,"mix":""},"places":[],"jobs":[],"geo":{"lat":52.4238516,"lon":13.3708589},"streetName":"Emilienstraße","streetNumber":"9"}