{"id":1844,"link":"KitaDetailsNeu.aspx?ID= 1844","num":6100270,"parent":"Ev. Kirchengemeinde Ernst-Moritz-Arndt","address":"Wilskistr. 53","district":"Zehlendorf","type":"Kindertagesstätte","parentType":"(Diakonisches Werk)","mapLink":"http://www.berlin.de/stadtplan/explorer?ADR_ZIP=14169&ADR_STREET=Wilskistra%c3%9fe&ADR_HOUSE=053","postcode":["14169"],"phone":"030813 46 53","email":"info@unserkindergarten.de","webLink":"http://","educational":["Situationsansatz"],"topics":[""],"languages":[""],"open":[["07:00","17:00"],["07:00","17:00"],["07:00","17:00"],["07:00","17:00"],["07:00","17:00"]],"structure":{"overall":60,"under":0,"over":60,"min":12,"mix":""},"places":[],"jobs":[],"geo":{"lat":52.4485957,"lon":13.2516003},"streetName":"Wilskistraße","streetNumber":"53"}