{"id":2644,"link":"KitaDetailsNeu.aspx?ID= 2644","num":3041410,"parent":"EKT Guckloch e.V.","address":"Liselotte-Herrmann-Str. 12","district":"Prenzlauer Berg","type":"Eltern-Initiativ-Kindertagesstätte","parentType":"(EKT)","mapLink":"http://www.berlin.de/stadtplan/explorer?ADR_ZIP=10407&ADR_STREET=Liselotte-Herrmann-Stra%c3%9fe&ADR_HOUSE=012","postcode":["10407"],"phone":"03042804111","email":"info@kita-guckloch.de","webLink":"http://www.kita-guckloch.de","educational":["Situationsansatz"],"topics":[""],"languages":[""],"open":[["08:00","17:00"],["08:00","17:00"],["08:00","17:00"],["08:00","17:00"],["08:00","17:00"]],"structure":{"overall":30,"under":13,"over":17,"min":12,"mix":""},"places":[],"jobs":[],"geo":{"lat":52.5313039,"lon":13.4355864},"streetName":"Liselotte-Herrmann-Straße","streetNumber":"12"}