{"id":2789,"link":"KitaDetailsNeu.aspx?ID= 2789","num":8142280,"parent":"Humanistischer Verband Deutschlands,\nLandesverband Berlin-Brandenburg e. V.","address":"Landreiterweg 55","district":"Buckow","type":"Kindertagesstätte","parentType":"(Sonstiger freier Träger)","mapLink":"http://www.berlin.de/stadtplan/explorer?ADR_ZIP=12353&ADR_STREET=Landreiterweg&ADR_HOUSE=055","postcode":["12353"],"phone":"030030-667 90 90","email":"landreiterweg@humanistischekitas.de","webLink":"http://www.humanistischekitas.de","image":"GibFoto.aspx?ID= 2789","educational":["Situationsansatz"],"topics":["Integration von Kindern mit Behinderung"],"languages":[""],"open":[["06:00","17:30"],["06:00","17:30"],["06:00","17:30"],["06:00","17:30"],["06:00","17:30"]],"structure":{"overall":140,"under":0,"over":140,"min":2,"mix":""},"places":[],"jobs":[],"geo":{"lat":52.4229844,"lon":13.4495867},"streetName":"Landreiterweg","streetNumber":"55"}