{"id":435179,"link":"KitaDetailsNeu.aspx?ID= 435179","num":11171360,"parent":"KiJuFa gemeinnützige UG\n(haftungsbeschränkt)","address":"Ehrlichstr. 21","district":"Karlshorst","type":"Kindertagesstätte","parentType":"(Sonstiger freier Träger)","mapLink":"http://www.berlin.de/stadtplan/explorer?ADR_ZIP=10318&ADR_STREET=Ehrlichstra%c3%9fe&ADR_HOUSE=021","postcode":["10318"],"phone":"03050014589","email":"info@kijufa-online.de","educational":[""],"topics":[""],"languages":[""],"open":[["08:00","17:00"],["08:00","17:00"],["08:00","17:00"],["08:00","17:00"],["08:00","17:00"]],"structure":{"overall":26,"under":10,"over":16,"min":12,"mix":""},"places":[],"jobs":[],"geo":{"lat":52.4798852,"lon":13.5208377},"streetName":"Ehrlichstraße","streetNumber":"21"}