{"id":468,"link":"KitaDetailsNeu.aspx?ID= 468","num":12200310,"parent":"Kindertagesstätten Nordwest Eigenbetrieb von Berlin","address":"Markgrafenstr. 14","district":"Frohnau","type":"Kindertagesstätte","parentType":"(Eigenbetrieb)","mapLink":"http://www.berlin.de/stadtplan/explorer?ADR_ZIP=13465&ADR_STREET=Markgrafenstra%c3%9fe&ADR_HOUSE=014","postcode":["13465"],"phone":"030406079980","email":"markgrafenstr@kita-nordwest.de","educational":["Situationsansatz"],"topics":[""],"languages":[""],"open":[["07:00","17:00"],["07:00","17:00"],["07:00","17:00"],["07:00","17:00"],["07:00","16:00"]],"structure":{"overall":61,"under":15,"over":46,"min":24,"mix":""},"places":[],"jobs":[],"geo":{"lat":52.63265,"lon":13.30409},"streetName":"Markgrafenstraße","streetNumber":"14"}