{"id":476129,"link":"KitaDetailsNeu.aspx?ID= 476129","num":3042190,"parent":"Kitanelle coccinelle e. V.","address":"Winsstr. 69","district":"Prenzlauer Berg","type":"Eltern-Initiativ-Kindertagesstätte","parentType":"(Sonstiger freier Träger)","mapLink":"http://www.berlin.de/stadtplan/explorer?ADR_ZIP=10405&ADR_STREET=Winsstra%c3%9fe&ADR_HOUSE=069","postcode":["10405"],"phone":"03012025459","email":"info@kitanelle-coccinelle.de","webLink":"http://www.kitanelle-coccinelle.de","educational":["bilingual (deutsch-französisch)"],"topics":[""],"languages":[""],"open":[0,0,0,0,0],"structure":{"overall":23,"under":8,"over":15,"min":12,"mix":""},"places":[],"jobs":[],"geo":{"lat":52.53194999999999,"lon":13.42316},"streetName":"Winsstraße","streetNumber":"69"}