{"id":550279,"link":"KitaDetailsNeu.aspx?ID= 550279","num":4073010,"parent":"Sinneswandel - Förderung gehörloser und \nhörgeschädigter Menschen in Berlin gGmbH","address":"Waldschulallee 31","district":"Westend","type":"Kindertagesstätte","parentType":"(Sonstiger freier Träger)","mapLink":"http://www.berlin.de/stadtplan/explorer?ADR_ZIP=14055&ADR_STREET=Waldschulallee&ADR_HOUSE=031","postcode":["14055"],"phone":"030030 55284041","email":"kita@sinneswandel-berlin.de","webLink":"http://www.sinneswandel-berlin.de/3f.php","image":"GibFoto.aspx?ID= 550279","educational":[""],"topics":["Integration von Kindern mit Behinderung"],"languages":[""],"open":[0,0,0,0,0],"structure":{"overall":65,"under":7,"over":58,"min":12,"mix":""},"places":[],"jobs":[],"geo":{"lat":52.49773,"lon":13.2649},"streetName":"Waldschulallee","streetNumber":"31"}