{"id":594,"link":"KitaDetailsNeu.aspx?ID= 594","num":10230900,"parent":"Gemeinnützige BOOT GmbH","address":"Albert-Kuntz-Str. 41","district":"Hellersdorf","type":"Kindertagesstätte","parentType":"(Sonstiger freier Träger)","mapLink":"http://www.berlin.de/stadtplan/explorer?ADR_ZIP=12627&ADR_STREET=Albert-Kuntz-Stra%c3%9fe&ADR_HOUSE=041","postcode":["12627"],"phone":"0309986002","email":"kirschbaum@bootkitas.de","webLink":"http://www.bootkitas.wordpress.com","image":"GibFoto.aspx?ID= 594","educational":["Situationsansatz"," Sonstiges"],"topics":["Ästhetische Bildung (Musik und Kunst)"," Gesundheit"," Integration von Kindern mit Behinderung"," Körper und Bewegung"," Natur- und Umweltpädagogik"],"languages":[""],"open":[["06:00","18:00"],["06:00","18:00"],["06:00","18:00"],["06:00","18:00"],["06:00","18:00"]],"structure":{"overall":167,"under":62,"over":105,"min":2,"mix":""},"places":[],"jobs":[],"geo":{"lat":52.53776999999999,"lon":13.61764},"streetName":"Albert-Kuntz-Straße","streetNumber":"41"}