{"id":643,"link":"KitaDetailsNeu.aspx?ID= 643","num":1031060,"parent":"AKILA (Arbeiterkinderladen) e. V.","address":"Antonstr. 19","district":"Wedding","type":"Kindertagesstätte","parentType":"(Sonstiger freier Träger)","mapLink":"http://www.berlin.de/stadtplan/explorer?ADR_ZIP=13347&ADR_STREET=Antonstra%c3%9fe&ADR_HOUSE=019","postcode":["13347"],"phone":"0304617000","email":"akila-e.v@arcor.de","educational":["Situationsansatz"],"topics":[""],"languages":["deutsch - türkisch"],"open":[["08:00","16:00"],["08:00","16:00"],["08:00","15:00"],["08:00","16:00"],["08:00","15:00"]],"structure":{"overall":25,"under":6,"over":19,"min":20,"mix":""},"places":[],"jobs":[],"geo":{"lat":52.5479038,"lon":13.3647665},"streetName":"Antonstraße","streetNumber":"19"}