{"id":647229,"link":"KitaDetailsNeu.aspx?ID= 647229","num":12202130,"parent":"Elisabethstift Jugendhilfe im Diakonischen Werk","address":"Fasanerie 10","district":"Lübars","type":"Kindertagesstätte","parentType":"(Diakonisches Werk)","mapLink":"http://www.berlin.de/stadtplan/explorer?ADR_ZIP=13469&ADR_STREET=Fasanerie&ADR_HOUSE=010","postcode":["13469"],"phone":"03040507198","email":"sandra.haase@elisabethstift-berlin.de","educational":[""],"topics":[""],"languages":[""],"open":[0,0,0,0,0],"structure":{"overall":30,"under":5,"over":25,"min":12,"mix":""},"places":[],"jobs":[],"geo":{"lat":52.60794,"lon":13.36796},"streetName":"Fasanerie","streetNumber":"10"}