{"id":688379,"link":"KitaDetailsNeu.aspx?ID= 688379","num":3192120,"parent":"MiNoMi gGmbH","address":"Bahnhofstr. 1","district":"Französisch Buchholz","type":"Kindertagesstätte","parentType":"(Sonstiger freier Träger)","mapLink":"http://www.berlin.de/stadtplan/explorer?ADR_ZIP=13129&ADR_STREET=Bahnhofstra%c3%9fe&ADR_HOUSE=001","postcode":["13129"],"phone":"03088763159","email":"info@kita-pankow.berlin","image":"GibFoto.aspx?ID= 688379","educational":[""],"topics":[""],"languages":[""],"open":[0,0,0,0,0],"structure":{"overall":41,"under":null,"over":null,"min":0,"mix":""},"places":[],"jobs":[],"geo":{"lat":52.5910498,"lon":13.4424268},"streetName":"Bahnhofstraße","streetNumber":"1"}