{"id":737229,"link":"KitaDetailsNeu.aspx?ID= 737229","num":9151410,"parent":"FreiRäume e. V.","address":"Mörikestr. 2","district":"Baumschulenweg","type":"Eltern-Initiativ-Kindertagesstätte","parentType":"(EKT)","mapLink":"http://www.berlin.de/stadtplan/explorer?ADR_ZIP=12437&ADR_STREET=M%c3%b6rikestra%c3%9fe&ADR_HOUSE=002","postcode":["12437"],"phone":"030","email":"kinderladen.baumschulenweg@gmail.com","educational":["Sonstiges"],"topics":[""],"languages":[""],"open":[0,0,0,0,0],"structure":{"overall":18,"under":null,"over":null,"min":12,"mix":""},"places":[],"jobs":[],"geo":{"lat":52.46641,"lon":13.48519},"streetName":"Mörikestraße","streetNumber":"2"}