{"id":752,"link":"KitaDetailsNeu.aspx?ID= 752","num":7110770,"parent":"Ev. Kirchengemeinde Zum Heilsbronnen","address":"Viktoria-Luise-Platz 1","district":"Schöneberg","type":"Kindertagesstätte","parentType":"(Diakonisches Werk)","mapLink":"http://www.berlin.de/stadtplan/explorer?ADR_ZIP=10777&ADR_STREET=Viktoria-Luise-Platz&ADR_HOUSE=001","postcode":["10777"],"phone":"030211 86 86","email":"post@heilsbronnen.de","image":"GibFoto.aspx?ID= 752","educational":[""],"topics":[""],"languages":[""],"open":[0,0,0,0,0],"structure":{"overall":54,"under":25,"over":29,"min":0,"mix":""},"places":[],"jobs":[],"geo":{"lat":52.4959165,"lon":13.3430695},"streetName":"Viktoria-Luise-Platz","streetNumber":"1"}