{"id":754229,"link":"KitaDetailsNeu.aspx?ID= 754229","num":4091970,"parent":"Edusation - gemeinnützige Gesellschaft für Integration und Sprachförderung mbH","address":"Brienner Str. 16","district":"Wilmersdorf","type":"Kindertagesstätte","parentType":"(Sonstiger freier Träger)","mapLink":"http://www.berlin.de/stadtplan/explorer?ADR_ZIP=10713&ADR_STREET=Brienner+Stra%c3%9fe&ADR_HOUSE=016","postcode":["10713"],"phone":"030","educational":[""],"topics":[""],"languages":[""],"open":[0,0,0,0,0],"structure":{"overall":null,"under":null,"over":null,"min":0,"mix":""},"places":[],"jobs":[],"geo":{"lat":52.4893604,"lon":13.3130686},"streetName":"Brienner Straße","streetNumber":"16"}