{"id":773229,"link":"KitaDetailsNeu.aspx?ID= 773229","num":1011390,"parent":"Jump Bilingual Kindergarten gUG","address":"An der Kolonnade 2","district":"Mitte","type":"Kindertagesstätte","parentType":"(Sonstiger freier Träger)","mapLink":"http://www.berlin.de/stadtplan/explorer?ADR_ZIP=10117&ADR_STREET=An+der+Kolonnade&ADR_HOUSE=002","postcode":["10117"],"phone":"030","educational":[""],"topics":[""],"languages":[""],"open":[0,0,0,0,0],"structure":{"overall":42,"under":null,"over":null,"min":0,"mix":""},"places":[],"jobs":[],"geo":{"lat":52.51236,"lon":13.38228},"streetName":"An der Kolonnade","streetNumber":"2"}